{
  "_note": "Manually update 'outcome' and 'outcome_note' as events resolve. outcome: null=pending, 'bull'=positive signal, 'bear'=negative signal, 'neutral'=mixed/in-line. static_gauges is intentionally empty — dealer gamma, DDR4 spot, and TSMC revenue removed (no free API); P/C OI, constituent corr, and HMM stress are now auto-computed by update_data.py. See WORKLOG.md entry 2026-07-02 for full rationale.",
  "static_gauges": {},
  "events": [
    {
      "tier": 4,
      "date": "2026-07-09",
      "event": "US CPI — June 2026",
      "ticker": null,
      "watch": "Any upside surprise → yield spike → SOXX same-day drag",
      "bull": "In-line or softer print; yields stable/falling",
      "bear": "Hot print + yields +8bp = likely −1 to −2% SOXX drag",
      "action_bull": "Removes macro headwind. No change to regime signal, but reduces near-term pressure.",
      "action_bear": "Hot print near a catalyst cluster = elevated crash risk. Confirms 4.7-4.8% TNX danger zone.",
      "outcome": null,
      "outcome_date": null,
      "outcome_note": null
    },
    {
      "tier": 1,
      "date": "2026-07-10",
      "event": "TSMC June 2026 Monthly Revenue",
      "ticker": "TSM",
      "watch": "NT$ revenue vs implied ~NT$422–443B to hit Q2 guide of $39–40.2B USD; Apr+May = NT$827.7B",
      "bull": "≥NT$422B = demand intact, Q2 guide on track",
      "bear": "<NT$410B = first crack in run-rate",
      "action_bull": "Q2 guide on track; fundamental demand floor intact. Does NOT change regime signal — tape still broken. Action: hold core, watch for +5% rally to trim into.",
      "action_bear": "First hard data point of demand softening. Adds fundamental reason to derisk beyond just tape/vol. Action: accelerate trimming on any bounce.",
      "outcome": null,
      "outcome_date": null,
      "outcome_note": null
    },
    {
      "tier": 1,
      "date": "2026-07-16",
      "event": "TSMC Q2 2026 Earnings + Call",
      "ticker": "TSM",
      "watch": "C.C. Wei language on: HBM demand, AI server 2H26 visibility, 3nm/5nm utilization, any guide raise",
      "bull": "Raises 2H26 outlook; 'demand outpacing supply'; HBM allocated through 2027",
      "bear": "'Visibility limited'; 'customers moderating'; any capex pull-back language",
      "action_bull": "Guidance raise narrative revives. Vol regime may begin to normalize — watch for RVol20 to start declining toward 60%. Action: begin rebuilding position if RVol also confirms.",
      "action_bear": "Broadcom pattern repeating (in-line but no raise = crash). Expect another −8 to −12% event. Action: be at reduced-core sizing BEFORE this event.",
      "outcome": null,
      "outcome_date": null,
      "outcome_note": null
    },
    {
      "tier": 2,
      "date": "2026-07-23",
      "event": "KLA Q4 FY2026 Earnings",
      "ticker": "KLAC",
      "watch": "Process control bookings, WFE spending outlook; Q3 FY26 revenue was $3.415B (+11.5% YoY)",
      "bull": "Bookings raised, WFE outlook upgraded again",
      "bear": "Bookings flat/down, customer push-outs",
      "action_bull": "Equipment backlog extending — confirms AI infrastructure demand is real and durable.",
      "action_bear": "First sign of equipment demand softening. Leading indicator: book-to-bill declining 12–18 months before revenue impact.",
      "outcome": null,
      "outcome_date": null,
      "outcome_note": null
    },
    {
      "tier": 1,
      "date": "2026-07-22",
      "event": "Alphabet Q2 2026 Earnings",
      "ticker": "GOOGL",
      "watch": "Google Cloud YoY growth (was +63% Q1), capex guidance vs $175–185B full year, AI infrastructure commentary",
      "bull": "Cloud growth ≥50%; capex raised/maintained; 'capacity constrained'",
      "bear": "Cloud deceleration; capex cut; efficiency-over-scale narrative",
      "action_bull": "Hyperscaler demand floor confirmed for one of four. Need all four to confirm for regime change.",
      "action_bear": "THIS IS THE THESIS-BREAK SCENARIO. At 42× fwd P/E with leverage in the basket, genuine capex reversal = 30–50% drawdown scenario. Action: sell, not trim.",
      "outcome": null,
      "outcome_date": null,
      "outcome_note": null
    },
    {
      "tier": 1,
      "date": "2026-07-28",
      "event": "Microsoft Q4 FY2026 Earnings",
      "ticker": "MSFT",
      "watch": "Azure growth (guided 39–40% CC), Q4 capex (guided >$40B), AI ARR growth (was $37B run rate, +123% YoY)",
      "bull": "Azure ≥39%; capex raised; AI ARR acceleration",
      "bear": "Azure miss; capex surprise cut; capacity commentary softens",
      "action_bull": "Second hyperscaler confirmed. Two of four checks.",
      "action_bear": "Capex cut from MSFT after GOOGL = consensus shift. Accelerate derisking.",
      "outcome": null,
      "outcome_date": null,
      "outcome_note": null
    },
    {
      "tier": 4,
      "date": "2026-07-29",
      "event": "FOMC July Meeting",
      "ticker": null,
      "watch": "Rate decision + Powell language on cuts",
      "bull": "Cut or explicitly dovish guidance; yields fall",
      "bear": "Hold + hawkish; or 'higher for longer' language",
      "action_bull": "Tailwind for 42× fwd P/E SOXX. Supports regime normalization if tape also heals.",
      "action_bear": "Headwind. Sustained TNX above 4.7–4.8% would pressure SOXX meaningfully at current valuation.",
      "outcome": null,
      "outcome_date": null,
      "outcome_note": null
    },
    {
      "tier": 1,
      "date": "2026-07-29",
      "event": "Meta Q2 2026 Earnings",
      "ticker": "META",
      "watch": "Capex guidance vs $125–145B (already raised from $115–135B), AI infra tone",
      "bull": "Capex raised again or held firm; ad revenue strong",
      "bear": "Capex cut; 'reassessing AI spend'; demand uncertainty",
      "action_bull": "Third hyperscaler confirmed. Three of four checks.",
      "action_bear": "META capex cut would be a major signal shift — they've been the most aggressive raiser.",
      "outcome": null,
      "outcome_date": null,
      "outcome_note": null
    },
    {
      "tier": 1,
      "date": "2026-07-30",
      "event": "Amazon Q2 2026 Earnings",
      "ticker": "AMZN",
      "watch": "AWS growth (was 28% Q1), capex vs ~$200B full-year guide (Q1 alone was $44.2B), AI chip revenue ($20B run rate)",
      "bull": "AWS ≥28%; capex maintained; chip demand commentary strong",
      "bear": "AWS deceleration; capex cut (Amazon FCF already going negative)",
      "action_bull": "ALL FOUR HYPERSCALERS CONFIRMED: demand floor locked. Check TSMC + Micron + equipment names too. If all confirm: fundamental case to reduce derisk posture.",
      "action_bear": "Fourth cut = thesis broken. This is the event that argues for selling, not trimming.",
      "outcome": null,
      "outcome_date": null,
      "outcome_note": null
    },
    {
      "tier": 2,
      "date": "2026-08-06",
      "event": "Lam Research Q4 FY2026 Earnings",
      "ticker": "LRCX",
      "watch": "Memory deposition/etch demand, HBM equipment backlog; Q2 FY26 revenue was $7.91B (+11.4% YoY), guidance 'equipment growth >30%'",
      "bull": "HBM demand 'sold out into 2027'; backlog extends",
      "bear": "Pull-in/push-out language; customer inventory caution",
      "action_bull": "HBM equipment confirming demand is real. Leading indicator for MU/SK Hynix capacity.",
      "action_bear": "Memory equipment softening = HBM demand peak signal. Watch MU price action.",
      "outcome": null,
      "outcome_date": null,
      "outcome_note": null
    },
    {
      "tier": 4,
      "date": "2026-08-07",
      "event": "US Jobs Report — July 2026",
      "ticker": null,
      "watch": "Jobs upside = yields up = SOXX pressure (Jun 5 mechanism)",
      "bull": "Soft/in-line print; no yield spike",
      "bear": "Hot print near a catalyst = elevated crash risk",
      "action_bull": "No macro headwind. Focus on tape healing.",
      "action_bear": "Hot jobs + high TNX + SOXX already stressed = Jun 5-style vulnerability.",
      "outcome": null,
      "outcome_date": null,
      "outcome_note": null
    },
    {
      "tier": 2,
      "date": "2026-08-14",
      "event": "Applied Materials Q3 FY2026 Earnings",
      "ticker": "AMAT",
      "watch": "WFE spending growth outlook (CEO Dickerson raised from 20% to >30% in May); token demand commentary",
      "bull": "'WFE growth accelerating further'; DRAM/HBM capacity tight",
      "bear": "Guidance walk-back; DRAM customer softness",
      "action_bull": "WFE upgrade = multi-year capex cycle intact.",
      "action_bear": "Walk-back from >30% WFE growth = major reversal signal.",
      "outcome": null,
      "outcome_date": null,
      "outcome_note": null
    },
    {
      "tier": 1,
      "date": "2026-09-04",
      "event": "Broadcom Q3 FY2026 Earnings",
      "ticker": "AVGO",
      "watch": "Q3 guide was ~$29.4B; AI revenue commentary — THIS CAUSED THE JUN 5 −10.4% CRASH",
      "bull": "Raises Q4 guide; AI segment raises; hyperscaler commentary strong",
      "bear": "Refuses to raise again (triggered Jun 5 crash); any AI softening",
      "action_bull": "Previous in-line report caused −10.4% crash. A raise here would be a major sentiment reversal.",
      "action_bear": "Second consecutive no-raise = pattern confirmed. Expect −10 to −15% event.",
      "outcome": null,
      "outcome_date": null,
      "outcome_note": null
    },
    {
      "tier": 1,
      "date": "2026-09-29",
      "event": "Micron Q4 FY2026 Earnings",
      "ticker": "MU",
      "watch": "Revenue vs $43.58B consensus; HBM shipment volumes; DRAM/NAND pricing outlook; Q1 FY27 guide",
      "bull": "Revenue beat + raised guide; HBM allocation sold out",
      "bear": "Revenue miss; softness in HBM pricing or allocation",
      "action_bull": "MU confirming HBM demand = SOXX fundamental thesis intact. Key regime-change confirmation.",
      "action_bear": "MU miss = memory cycle turn. HBM pricing softness would be the first crack in the AI spending thesis.",
      "outcome": null,
      "outcome_date": null,
      "outcome_note": null
    }
  ]
}
